animesubinfo_cli/__init__.py
animesubinfo_cli/__main__.py
animesubinfo_cli/cli.py
animesubinfo_cli/commands/__init__.py
animesubinfo_cli/commands/best.py
animesubinfo_cli/commands/download.py
animesubinfo_cli/commands/find.py
animesubinfo_cli/commands/search.py
animesubinfo_cli/output.py
animesubinfo_cli-0.1.0.dist-info/WHEEL
animesubinfo_cli-0.1.0.dist-info/entry_points.txt
animesubinfo_cli-0.1.0.dist-info/METADATA
animesubinfo_cli-0.1.0.dist-info/RECORD
