Metadata-Version: 2.3
Name: animesubinfo-cli
Version: 0.1.0
Summary: Command-line interface for animesubinfo
Author: Adrian Lehmann
Author-email: Adrian Lehmann <ownadi@gmail.com>
Requires-Dist: animesubinfo
Requires-Dist: typer>=0.15.0
Requires-Dist: rich>=13.9.0
Requires-Python: >=3.13
